Metadata-Version: 1.0
Name: dwk-distributions
Version: 0.2
Summary: Gaussian and Binomial distributions
Home-page: UNKNOWN
Author: Dongwon Kim
Author-email: astro.dw.kim@gmail.com
License: UNKNOWN
Platform: UNKNOWN
